pyasync_orm/__init__.py
pyasync_orm/clients/__init__.py
pyasync_orm/clients/abstract_client.py
pyasync_orm/clients/asyncpg_client.py
pyasync_orm/database.py
pyasync_orm/fields.py
pyasync_orm/models.py
pyasync_orm/orm.py
pyasync_orm/sql.py
pyasync_orm-0.1.2.dist-info/WHEEL
pyasync_orm-0.1.2.dist-info/METADATA
pyasync_orm-0.1.2.dist-info/RECORD
